{
  "scenario_id": "benchmark-phase-only",
  "run_root": "/app/runs/rbe-phase-only-master-ref-20260705-integration-gate",
  "base": {
    "side": "base",
    "ref": "master",
    "repo_root": "/app/runs/rbe-phase-only-master-ref-20260705-integration-gate/checkouts/base",
    "run_dir": "/app/runs/rbe-phase-only-master-ref-20260705-integration-gate/base",
    "parset_path": "/app/runs/master-benchmark-phase-only-manual/inputs/master_benchmark_phase_only.parset",
    "work_dir": "/tmp/rbe-master-phase-only-work",
    "command": [],
    "returncode": 0,
    "log_path": "/app/runs/rbe-phase-only-master-ref-20260705-integration-gate/base/rapthor-command.log",
    "input_snapshot": {
      "parset": "inputs/base/master_benchmark_phase_only.parset",
      "strategy": "inputs/base/master_benchmark_phase_only_strategy.py"
    }
  },
  "current": {
    "side": "current",
    "ref": "current",
    "repo_root": "/app",
    "run_dir": "/app/runs/rbe-phase-only-master-ref-20260705-integration-gate/current",
    "parset_path": "/app/runs/current-benchmark-phase-only-manual/inputs/current_benchmark_phase_only.parset",
    "work_dir": "/tmp/rbe-current-phase-only-work",
    "command": [],
    "returncode": 0,
    "log_path": "/app/runs/rbe-phase-only-master-ref-20260705-integration-gate/current/rapthor-command.log",
    "input_snapshot": {
      "parset": "inputs/current/current_benchmark_phase_only.parset",
      "strategy": "inputs/current/current_benchmark_phase_only_strategy.py"
    }
  },
  "comparison": {
    "passed": false,
    "metrics": {
      "base_operations": 12,
      "current_operations": 12,
      "operations": 12,
      "output_records": 12,
      "fits": 28,
      "h5": 8,
      "text": 37,
      "fits_image_hdus": 24,
      "fits_table_hdus": 4,
      "diagnostics": 4,
      "visual_comparisons": 20
    },
    "product_statistics": {
      "fits": [
        {
          "product": "field-MFS-dirty.fits.fz",
          "kind": "image",
          "hdu_index": 1,
          "hdu_name": "COMPRESSED_IMAGE",
          "shape": [
            1,
            1,
            2400,
            2400
          ],
          "reference_count": 5760000,
          "reference_mean": -0.0003774843257898413,
          "reference_std": 0.17277689489694525,
          "reference_rms": 0.17277730726182264,
          "reference_min": -0.7161927819252014,
          "reference_max": 4.523244380950928,
          "current_count": 5760000,
          "current_mean": -0.00037748867642461645,
          "current_std": 0.172776895600386,
          "current_rms": 0.1727773079747671,
          "current_min": -0.7161921858787537,
          "current_max": 4.523251533508301,
          "residual_count": 5760000,
          "residual_mean": -4.350634775215256e-09,
          "residual_std": 4.15530104113912e-06,
          "residual_rms": 4.1553033187139075e-06,
          "residual_min": -1.4469027519226074e-05,
          "residual_max": 1.4659017324447632e-05,
          "reference_mad_std": 0.15487262132924515,
          "residual_mad_std": 4.280414432287216e-06,
          "max_abs_delta": 1.4659017324447632e-05,
          "max_relative_delta": 10.472217645940418,
          "p50_abs_delta": 2.8908252716064453e-06,
          "p95_abs_delta": 7.994472980499268e-06,
          "p99_abs_delta": 9.939074516296387e-06,
          "p999_abs_delta": 1.1682510375976562e-05,
          "residual_rms_over_reference_rms": 2.4050052547798187e-05,
          "residual_rms_over_reference_mad_std": 2.683045772099453e-05,
          "planes": [
            {
              "plane": 0,
              "leading_index": [
                0,
                0
              ],
              "max_abs_delta": 1.4659017324447632e-05,
              "p99_abs_delta": 9.939074516296387e-06,
              "residual_rms": 4.1553033187139075e-06
            }
          ]
        },
        {
          "product": "field-MFS-image-pb-ast.fits.fz",
          "kind": "image",
          "hdu_index": 1,
          "hdu_name": "COMPRESSED_IMAGE",
          "shape": [
            1,
            1,
            2400,
            2400
          ],
          "reference_count": 5760000,
          "reference_mean": 0.002738809223950744,
          "reference_std": 0.08419838157167883,
          "reference_rms": 0.08424291385781495,
          "reference_min": -0.18066555261611938,
          "reference_max": 4.561816692352295,
          "current_count": 5760000,
          "current_mean": 0.0027388123778992425,
          "current_std": 0.08419838247031212,
          "current_rms": 0.08424291485851085,
          "current_min": -0.1806642711162567,
          "current_max": 4.5618157386779785,
          "residual_count": 5760000,
          "residual_mean": 3.153948502407983e-09,
          "residual_std": 7.63295110207222e-06,
          "residual_rms": 7.632951753680657e-06,
          "residual_min": -4.281289875507355e-06,
          "residual_max": 0.018093821592628956,
          "reference_mad_std": 0.04171156301591545,
          "residual_mad_std": 1.2316547334194183e-06,
          "max_abs_delta": 0.018093821592628956,
          "max_relative_delta": 9.135809162757038,
          "p50_abs_delta": 8.307397365570068e-07,
          "p95_abs_delta": 2.294778823852539e-06,
          "p99_abs_delta": 2.8472859412431717e-06,
          "p999_abs_delta": 3.4049153327941895e-06,
          "residual_rms_over_reference_rms": 9.06064546457111e-05,
          "residual_rms_over_reference_mad_std": 0.0001829936641493926,
          "planes": [
            {
              "plane": 0,
              "leading_index": [
                0,
                0
              ],
              "max_abs_delta": 0.018093821592628956,
              "p99_abs_delta": 2.8472859412431717e-06,
              "residual_rms": 7.632951753680657e-06
            }
          ]
        },
        {
          "product": "field-MFS-image-pb.fits.fz",
          "kind": "image",
          "hdu_index": 1,
          "hdu_name": "COMPRESSED_IMAGE",
          "shape": [
            1,
            1,
            2400,
            2400
          ],
          "reference_count": 5760000,
          "reference_mean": 0.002738809223950744,
          "reference_std": 0.08419838157167883,
          "reference_rms": 0.08424291385781495,
          "reference_min": -0.18066555261611938,
          "reference_max": 4.561816692352295,
          "current_count": 5760000,
          "current_mean": 0.0027388125597003436,
          "current_std": 0.08419838207046529,
          "current_rms": 0.08424291446478574,
          "current_min": -0.18066436052322388,
          "current_max": 4.5618157386779785,
          "residual_count": 5760000,
          "residual_mean": 3.3357496008940003e-09,
          "residual_std": 7.632750247295944e-06,
          "residual_rms": 7.632750976209149e-06,
          "residual_min": -4.254281520843506e-06,
          "residual_max": 0.01809362042695284,
          "reference_mad_std": 0.04171156301591545,
          "residual_mad_std": 1.2294109677895903e-06,
          "max_abs_delta": 0.01809362042695284,
          "max_relative_delta": 9.13570759155398,
          "p50_abs_delta": 8.292263373732567e-07,
          "p95_abs_delta": 2.291053533554077e-06,
          "p99_abs_delta": 2.8461217880249023e-06,
          "p999_abs_delta": 3.4086406230926514e-06,
          "residual_rms_over_reference_rms": 9.060407132986513e-05,
          "residual_rms_over_reference_mad_std": 0.00018298885067665288,
          "planes": [
            {
              "plane": 0,
              "leading_index": [
                0,
                0
              ],
              "max_abs_delta": 0.01809362042695284,
              "p99_abs_delta": 2.8461217880249023e-06,
              "residual_rms": 7.632750976209149e-06
            }
          ]
        },
        {
          "product": "field-MFS-image.fits.fz",
          "kind": "image",
          "hdu_index": 1,
          "hdu_name": "COMPRESSED_IMAGE",
          "shape": [
            1,
            1,
            2400,
            2400
          ],
          "reference_count": 5760000,
          "reference_mean": 0.0026982227209324037,
          "reference_std": 0.082947918481259,
          "reference_rms": 0.08299179228228137,
          "reference_min": -0.1779799908399582,
          "reference_max": 4.561807155609131,
          "current_count": 5760000,
          "current_mean": 0.0026982256911393084,
          "current_std": 0.08294792041258801,
          "current_rms": 0.08299179430915662,
          "current_min": -0.17798006534576416,
          "current_max": 4.561809539794922,
          "residual_count": 5760000,
          "residual_mean": 2.970206906324966e-09,
          "residual_std": 7.478623921301676e-06,
          "residual_rms": 7.478624511124676e-06,
          "residual_min": -4.1425228118896484e-06,
          "residual_max": 0.01772800786420703,
          "reference_mad_std": 0.04086865414045751,
          "residual_mad_std": 1.2040391564369201e-06,
          "max_abs_delta": 0.01772800786420703,
          "max_relative_delta": 9.135125232243718,
          "p50_abs_delta": 8.121132850646973e-07,
          "p95_abs_delta": 2.2472813725471497e-06,
          "p99_abs_delta": 2.7939677238464355e-06,
          "p999_abs_delta": 3.3369287848472595e-06,
          "residual_rms_over_reference_rms": 9.011282086411033e-05,
          "residual_rms_over_reference_mad_std": 0.00018299170032421713,
          "planes": [
            {
              "plane": 0,
              "leading_index": [
                0,
                0
              ],
              "max_abs_delta": 0.01772800786420703,
              "p99_abs_delta": 2.7939677238464355e-06,
              "residual_rms": 7.478624511124676e-06
            }
          ]
        },
        {
          "product": "field-MFS-model-pb.fits.fz",
          "kind": "image",
          "hdu_index": 1,
          "hdu_name": "COMPRESSED_IMAGE",
          "shape": [
            1,
            1,
            2400,
            2400
          ],
          "reference_count": 5760000,
          "reference_mean": 4.7103404124699475e-06,
          "reference_std": 0.0030398209669020232,
          "reference_rms": 0.0030398246163428604,
          "reference_min": -0.11773659288883209,
          "reference_max": 1.6757864952087402,
          "current_count": 5760000,
          "current_mean": 5.100968439431957e-06,
          "current_std": 0.0030222728774504212,
          "current_rms": 0.0030222771821346037,
          "current_min": -0.11773661524057388,
          "current_max": 1.6649447679519653,
          "residual_count": 5760000,
          "residual_mean": 3.9062802696200945e-07,
          "residual_std": 0.003443491658413036,
          "residual_rms": 0.003443491680569351,
          "residual_min": -0.23139111697673798,
          "residual_max": 0.23094793409109116,
          "reference_mad_std": 0.0,
          "residual_mad_std": 0.0,
          "max_abs_delta": 0.23139111697673798,
          "max_relative_delta": 10483.053367195718,
          "p50_abs_delta": 0.0,
          "p95_abs_delta": 0.0,
          "p99_abs_delta": 0.0,
          "p999_abs_delta": 0.05378733335063006,
          "residual_rms_over_reference_rms": 1.1327928795813662,
          "residual_rms_over_reference_mad_std": null,
          "planes": [
            {
              "plane": 0,
              "leading_index": [
                0,
                0
              ],
              "max_abs_delta": 0.23139111697673798,
              "p99_abs_delta": 0.0,
              "residual_rms": 0.003443491680569351
            }
          ]
        },
        {
          "product": "field-MFS-residual.fits.fz",
          "kind": "image",
          "hdu_index": 1,
          "hdu_name": "COMPRESSED_IMAGE",
          "shape": [
            1,
            1,
            2400,
            2400
          ],
          "reference_count": 5760000,
          "reference_mean": -0.0002454581008149913,
          "reference_std": 0.04169940500257148,
          "reference_rms": 0.04170012742483816,
          "reference_min": -0.17798076570034027,
          "reference_max": 0.20548607409000397,
          "current_count": 5760000,
          "current_mean": -0.0002454549767627429,
          "current_std": 0.04169940411507645,
          "current_rms": 0.04170012651896964,
          "current_min": -0.1779802292585373,
          "current_max": 0.20548602938652039,
          "residual_count": 5760000,
          "residual_mean": 3.124052248119037e-09,
          "residual_std": 7.4771547843296056e-06,
          "residual_rms": 7.477155436964352e-06,
          "residual_min": -4.227273166179657e-06,
          "residual_max": 0.017727395053952932,
          "reference_mad_std": 0.04074424467167118,
          "residual_mad_std": 1.1985160410404205e-06,
          "max_abs_delta": 0.017727395053952932,
          "max_relative_delta": 9.130927028215257,
          "p50_abs_delta": 8.083879947662354e-07,
          "p95_abs_delta": 2.2314488887786865e-06,
          "p99_abs_delta": 2.773478627204895e-06,
          "p999_abs_delta": 3.3155083656311035e-06,
          "residual_rms_over_reference_rms": 0.00017930773594017073,
          "residual_rms_over_reference_mad_std": 0.0001835143956457511,
          "planes": [
            {
              "plane": 0,
              "leading_index": [
                0,
                0
              ],
              "max_abs_delta": 0.017727395053952932,
              "p99_abs_delta": 2.773478627204895e-06,
              "residual_rms": 7.477155436964352e-06
            }
          ]
        },
        {
          "product": "field-MFS-dirty.fits.fz",
          "kind": "image",
          "hdu_index": 1,
          "hdu_name": "COMPRESSED_IMAGE",
          "shape": [
            1,
            1,
            2400,
            2400
          ],
          "reference_count": 5760000,
          "reference_mean": -0.0004146042389182429,
          "reference_std": 0.17188782973264022,
          "reference_rms": 0.1718883297576426,
          "reference_min": -0.713736891746521,
          "reference_max": 4.504077911376953,
          "current_count": 5760000,
          "current_mean": -0.000414604295841514,
          "current_std": 0.1718878266701589,
          "current_rms": 0.17188832669530754,
          "current_min": -0.7137433290481567,
          "current_max": 4.5040669441223145,
          "residual_count": 5760000,
          "residual_mean": -5.692327095100662e-11,
          "residual_std": 4.157352385581049e-06,
          "residual_rms": 4.157352385970752e-06,
          "residual_min": -1.4044344425201416e-05,
          "residual_max": 1.4096498489379883e-05,
          "reference_mad_std": 0.1547506735302508,
          "residual_mad_std": 4.2859375476837155e-06,
          "max_abs_delta": 1.4096498489379883e-05,
          "max_relative_delta": 10.448531440943043,
          "p50_abs_delta": 2.8908252716064453e-06,
          "p95_abs_delta": 8.001923561096191e-06,
          "p99_abs_delta": 9.901821613311768e-06,
          "p999_abs_delta": 1.1622905731201172e-05,
          "residual_rms_over_reference_rms": 2.4186356292090885e-05,
          "residual_rms_over_reference_mad_std": 2.686484194951222e-05,
          "planes": [
            {
              "plane": 0,
              "leading_index": [
                0,
                0
              ],
              "max_abs_delta": 1.4096498489379883e-05,
              "p99_abs_delta": 9.901821613311768e-06,
              "residual_rms": 4.157352385970752e-06
            }
          ]
        },
        {
          "product": "field-MFS-image-pb-ast.fits.fz",
          "kind": "image",
          "hdu_index": 1,
          "hdu_name": "COMPRESSED_IMAGE",
          "shape": [
            1,
            1,
            2400,
            2400
          ],
          "reference_count": 5760000,
          "reference_mean": 0.0027456508617726013,
          "reference_std": 0.08659570560395154,
          "reference_rms": 0.08663922222470033,
          "reference_min": -0.20545564591884613,
          "reference_max": 4.64818000793457,
          "current_count": 5760000,
          "current_mean": 0.0027456956323029173,
          "current_std": 0.08659480155615425,
          "current_rms": 0.08663832004981964,
          "current_min": -0.20545412600040436,
          "current_max": 4.648212432861328,
          "residual_count": 5760000,
          "residual_mean": 4.47705303187824e-08,
          "residual_std": 8.313822277349365e-05,
          "residual_rms": 8.313823482811896e-05,
          "residual_min": -0.052141185849905014,
          "residual_max": 0.037436818704009056,
          "reference_mad_std": 0.045739252114668484,
          "residual_mad_std": 3.489228151738643e-05,
          "max_abs_delta": 0.052141185849905014,
          "max_relative_delta": 259.6709449834212,
          "p50_abs_delta": 2.3536384105682373e-05,
          "p95_abs_delta": 7.841736078262329e-05,
          "p99_abs_delta": 0.0001289844512939453,
          "p999_abs_delta": 0.00021427579049486986,
          "residual_rms_over_reference_rms": 0.0009595911954576244,
          "residual_rms_over_reference_mad_std": 0.001817656192097131,
          "planes": [
            {
              "plane": 0,
              "leading_index": [
                0,
                0
              ],
              "max_abs_delta": 0.052141185849905014,
              "p99_abs_delta": 0.0001289844512939453,
              "residual_rms": 8.313823482811896e-05
            }
          ]
        },
        {
          "product": "field-MFS-image-pb.fits.fz",
          "kind": "image",
          "hdu_index": 1,
          "hdu_name": "COMPRESSED_IMAGE",
          "shape": [
            1,
            1,
            2400,
            2400
          ],
          "reference_count": 5760000,
          "reference_mean": 0.0027456508617726013,
          "reference_std": 0.08659570560395154,
          "reference_rms": 0.08663922222470033,
          "reference_min": -0.20545564591884613,
          "reference_max": 4.64818000793457,
          "current_count": 5760000,
          "current_mean": 0.002745695897751369,
          "current_std": 0.08659480132818557,
          "current_rms": 0.08663831983037795,
          "current_min": -0.20545461773872375,
          "current_max": 4.6482110023498535,
          "residual_count": 5760000,
          "residual_mean": 4.503597876811307e-08,
          "residual_std": 8.313732974747833e-05,
          "residual_rms": 8.313734194560421e-05,
          "residual_min": -0.05214239377528429,
          "residual_max": 0.037436059676110744,
          "reference_mad_std": 0.045739252114668484,
          "residual_mad_std": 3.489366229623556e-05,
          "max_abs_delta": 0.05214239377528429,
          "max_relative_delta": 259.639914595037,
          "p50_abs_delta": 2.3536180378869176e-05,
          "p95_abs_delta": 7.841363549232483e-05,
          "p99_abs_delta": 0.00012901145964860916,
          "p999_abs_delta": 0.0002143029142171165,
          "residual_rms_over_reference_rms": 0.000959580889703581,
          "residual_rms_over_reference_mad_std": 0.0018176366709533984,
          "planes": [
            {
              "plane": 0,
              "leading_index": [
                0,
                0
              ],
              "max_abs_delta": 0.05214239377528429,
              "p99_abs_delta": 0.00012901145964860916,
              "residual_rms": 8.313734194560421e-05
            }
          ]
        },
        {
          "product": "field-MFS-image.fits.fz",
          "kind": "image",
          "hdu_index": 1,
          "hdu_name": "COMPRESSED_IMAGE",
          "shape": [
            1,
            1,
            2400,
            2400
          ],
          "reference_count": 5760000,
          "reference_mean": 0.002705599722726068,
          "reference_std": 0.08529322066965452,
          "reference_rms": 0.08533612225817384,
          "reference_min": -0.2024054080247879,
          "reference_max": 4.648171901702881,
          "current_count": 5760000,
          "current_mean": 0.0027056443652658433,
          "current_std": 0.08529233805845937,
          "current_rms": 0.08533524150613167,
          "current_min": -0.20240464806556702,
          "current_max": 4.648200035095215,
          "residual_count": 5760000,
          "residual_mean": 4.46425397706254e-08,
          "residual_std": 8.230195042510992e-05,
          "residual_rms": 8.230196253269788e-05,
          "residual_min": -0.05199414771050215,
          "residual_max": 0.03715079836547375,
          "reference_mad_std": 0.04482100436380715,
          "residual_mad_std": 3.416046872735023e-05,
          "max_abs_delta": 0.05199414771050215,
          "max_relative_delta": 256.97497189757786,
          "p50_abs_delta": 2.304092049598694e-05,
          "p95_abs_delta": 7.708743214607239e-05,
          "p99_abs_delta": 0.0001267567276954651,
          "p999_abs_delta": 0.00021040441095830642,
          "residual_rms_over_reference_rms": 0.0009644446027639212,
          "residual_rms_over_reference_mad_std": 0.0018362364632586528,
          "planes": [
            {
              "plane": 0,
              "leading_index": [
                0,
                0
              ],
              "max_abs_delta": 0.05199414771050215,
              "p99_abs_delta": 0.0001267567276954651,
              "residual_rms": 8.230196253269788e-05
            }
          ]
        },
        {
          "product": "field-MFS-model-pb.fits.fz",
          "kind": "image",
          "hdu_index": 1,
          "hdu_name": "COMPRESSED_IMAGE",
          "shape": [
            1,
            1,
            2400,
            2400
          ],
          "reference_count": 5760000,
          "reference_mean": 4.498946343206484e-06,
          "reference_std": 0.002774606110503227,
          "reference_rms": 0.0027746097579587504,
          "reference_min": -0.08346667885780334,
          "reference_max": 2.806748867034912,
          "current_count": 5760000,
          "current_mean": 4.6421932765709705e-06,
          "current_std": 0.002772436159468202,
          "current_rms": 0.0027724400459316315,
          "current_min": -0.08346669375896454,
          "current_max": 2.806363582611084,
          "residual_count": 5760000,
          "residual_mean": 1.4324693336448628e-07,
          "residual_std": 0.0027073598033519417,
          "residual_rms": 0.0027073598071415557,
          "residual_min": -0.16418200731277466,
          "residual_max": 0.16224797815084457,
          "reference_mad_std": 0.0,
          "residual_mad_std": 0.0,
          "max_abs_delta": 0.16418200731277466,
          "max_relative_delta": 10271.36976073243,
          "p50_abs_delta": 0.0,
          "p95_abs_delta": 0.0,
          "p99_abs_delta": 0.0,
          "p999_abs_delta": 0.04323478235305178,
          "residual_rms_over_reference_rms": 0.9757623750063253,
          "residual_rms_over_reference_mad_std": null,
          "planes": [
            {
              "plane": 0,
              "leading_index": [
                0,
                0
              ],
              "max_abs_delta": 0.16418200731277466,
              "p99_abs_delta": 0.0,
              "residual_rms": 0.0027073598071415557
            }
          ]
        },
        {
          "product": "field-MFS-residual.fits.fz",
          "kind": "image",
          "hdu_index": 1,
          "hdu_name": "COMPRESSED_IMAGE",
          "shape": [
            1,
            1,
            2400,
            2400
          ],
          "reference_count": 5760000,
          "reference_mean": -0.00020926457559866532,
          "reference_std": 0.04553727565466903,
          "reference_rms": 0.04553775648527177,
          "reference_min": -0.20240744948387146,
          "reference_max": 0.22172680497169495,
          "current_count": 5760000,
          "current_mean": -0.00020919075952053741,
          "current_std": 0.04553504996356018,
          "current_rms": 0.04553553047849329,
          "current_min": -0.20240382850170135,
          "current_max": 0.22173084318637848,
          "residual_count": 5760000,
          "residual_mean": 7.381607812790607e-08,
          "residual_std": 8.696188578232742e-05,
          "residual_rms": 8.69619171110662e-05,
          "residual_min": -0.05199167225509882,
          "residual_max": 0.03715014923363924,
          "reference_mad_std": 0.044675488180085085,
          "residual_mad_std": 3.416046872735023e-05,
          "max_abs_delta": 0.05199167225509882,
          "max_relative_delta": 258.8510501427763,
          "p50_abs_delta": 2.304092049598694e-05,
          "p95_abs_delta": 7.741153240203857e-05,
          "p99_abs_delta": 0.0001301020383834839,
          "p999_abs_delta": 0.0004959292747080367,
          "residual_rms_over_reference_rms": 0.0019096662598912224,
          "residual_rms_over_reference_mad_std": 0.001946524160195547,
          "planes": [
            {
              "plane": 0,
              "leading_index": [
                0,
                0
              ],
              "max_abs_delta": 0.05199167225509882,
              "p99_abs_delta": 0.0001301020383834839,
              "residual_rms": 8.69619171110662e-05
            }
          ]
        },
        {
          "product": "field-MFS-dirty.fits.fz",
          "kind": "image",
          "hdu_index": 1,
          "hdu_name": "COMPRESSED_IMAGE",
          "shape": [
            1,
            1,
            2400,
            2400
          ],
          "reference_count": 5760000,
          "reference_mean": -0.0004278708902219155,
          "reference_std": 0.17184632842284897,
          "reference_rms": 0.1718468610883315,
          "reference_min": -0.715177059173584,
          "reference_max": 4.508828163146973,
          "current_count": 5760000,
          "current_mean": -0.0004277967848059057,
          "current_std": 0.17184569848308662,
          "current_rms": 0.17184623096602683,
          "current_min": -0.7151928544044495,
          "current_max": 4.50886869430542,
          "residual_count": 5760000,
          "residual_mean": 7.410541601002396e-08,
          "residual_std": 8.179606891207373e-05,
          "residual_rms": 8.17961024809948e-05,
          "residual_min": -0.0016504526138305664,
          "residual_max": 0.001531362533569336,
          "reference_mad_std": 0.1547236104374053,
          "residual_mad_std": 3.700487315654755e-05,
          "max_abs_delta": 0.0016504526138305664,
          "max_relative_delta": 261.45178213710096,
          "p50_abs_delta": 2.49519944190979e-05,
          "p95_abs_delta": 0.00018147379159927368,
          "p99_abs_delta": 0.00027060514781623943,
          "p999_abs_delta": 0.00043351393006745877,
          "residual_rms_over_reference_rms": 0.00047598252282856973,
          "residual_rms_over_reference_mad_std": 0.0005286594738175793,
          "planes": [
            {
              "plane": 0,
              "leading_index": [
                0,
                0
              ],
              "max_abs_delta": 0.0016504526138305664,
              "p99_abs_delta": 0.00027060514781623943,
              "residual_rms": 8.17961024809948e-05
            }
          ]
        },
        {
          "product": "field-MFS-image-pb-ast.fits.fz",
          "kind": "image",
          "hdu_index": 1,
          "hdu_name": "COMPRESSED_IMAGE",
          "shape": [
            1,
            1,
            2400,
            2400
          ],
          "reference_count": 5760000,
          "reference_mean": 0.002727698624875785,
          "reference_std": 0.08687953193461835,
          "reference_rms": 0.08692234125336536,
          "reference_min": -0.22482915222644806,
          "reference_max": 4.668468475341797,
          "current_count": 5760000,
          "current_mean": 0.0027277309225184313,
          "current_std": 0.08687956036930027,
          "current_rms": 0.08692237068757704,
          "current_min": -0.2248084396123886,
          "current_max": 4.668703556060791,
          "residual_count": 5760000,
          "residual_mean": 3.229764264769813e-08,
          "residual_std": 0.0001958646208227545,
          "residual_rms": 0.00019586462348565944,
          "residual_min": -0.05334220128133893,
          "residual_max": 0.06172359955962747,
          "reference_mad_std": 0.046291435630229534,
          "residual_mad_std": 0.00014711232092231511,
          "max_abs_delta": 0.06172359955962747,
          "max_relative_delta": 404.85606484708114,
          "p50_abs_delta": 9.922496974468231e-05,
          "p95_abs_delta": 0.0002979487180709839,
          "p99_abs_delta": 0.0004034182149916885,
          "p999_abs_delta": 0.0006220341324806866,
          "residual_rms_over_reference_rms": 0.0022533288986630487,
          "residual_rms_over_reference_mad_std": 0.0042311200942265585,
          "planes": [
            {
              "plane": 0,
              "leading_index": [
                0,
                0
              ],
              "max_abs_delta": 0.06172359955962747,
              "p99_abs_delta": 0.0004034182149916885,
              "residual_rms": 0.00019586462348565944
            }
          ]
        },
        {
          "product": "field-MFS-image-pb.fits.fz",
          "kind": "image",
          "hdu_index": 1,
          "hdu_name": "COMPRESSED_IMAGE",
          "shape": [
            1,
            1,
            2400,
            2400
          ],
          "reference_count": 5760000,
          "reference_mean": 0.002727698624875785,
          "reference_std": 0.08687953193461835,
          "reference_rms": 0.08692234125336536,
          "reference_min": -0.22482915222644806,
          "reference_max": 4.668468475341797,
          "current_count": 5760000,
          "current_mean": 0.0027277309516026004,
          "current_std": 0.08687956025891479,
          "current_rms": 0.08692237057815858,
          "current_min": -0.22481229901313782,
          "current_max": 4.668701171875,
          "residual_count": 5760000,
          "residual_mean": 3.232672681767283e-08,
          "residual_std": 0.00019586365488513828,
          "residual_rms": 0.00019586365755285446,
          "residual_min": -0.05334088625386357,
          "residual_max": 0.061724577797576785,
          "reference_mad_std": 0.046291435630229534,
          "residual_mad_std": 0.00014711370170116423,
          "max_abs_delta": 0.061724577797576785,
          "max_relative_delta": 408.3401717025481,
          "p50_abs_delta": 9.922683238983154e-05,
          "p95_abs_delta": 0.0002979561686515808,
          "p99_abs_delta": 0.0004034265875816345,
          "p999_abs_delta": 0.0006222389824688639,
          "residual_rms_over_reference_rms": 0.0022533177860677013,
          "residual_rms_over_reference_mad_std": 0.004231099227887205,
          "planes": [
            {
              "plane": 0,
              "leading_index": [
                0,
                0
              ],
              "max_abs_delta": 0.061724577797576785,
              "p99_abs_delta": 0.0004034265875816345,
              "residual_rms": 0.00019586365755285446
            }
          ]
        },
        {
          "product": "field-MFS-image.fits.fz",
          "kind": "image",
          "hdu_index": 1,
          "hdu_name": "COMPRESSED_IMAGE",
          "shape": [
            1,
            1,
            2400,
            2400
          ],
          "reference_count": 5760000,
          "reference_mean": 0.002688267188744597,
          "reference_std": 0.08557537644940577,
          "reference_rms": 0.08561759068635136,
          "reference_min": -0.22454942762851715,
          "reference_max": 4.668456077575684,
          "current_count": 5760000,
          "current_mean": 0.0026882966019585435,
          "current_std": 0.08557541717227085,
          "current_rms": 0.08561763231267434,
          "current_min": -0.22453010082244873,
          "current_max": 4.668686866760254,
          "residual_count": 5760000,
          "residual_mean": 2.9413213945536333e-08,
          "residual_std": 0.00019262857366842914,
          "residual_rms": 0.0001926285759140388,
          "residual_min": -0.053309441078454256,
          "residual_max": 0.06168219819664955,
          "reference_mad_std": 0.045360428749263514,
          "residual_mad_std": 0.0001441489969147369,
          "max_abs_delta": 0.06168219819664955,
          "max_relative_delta": 414.08366092809956,
          "p50_abs_delta": 9.722867980599403e-05,
          "p95_abs_delta": 0.00029175267554819567,
          "p99_abs_delta": 0.0003950074315071106,
          "p999_abs_delta": 0.0006124973297119141,
          "residual_rms_over_reference_rms": 0.0022498714851683682,
          "residual_rms_over_reference_mad_std": 0.004246621586820128,
          "planes": [
            {
              "plane": 0,
              "leading_index": [
                0,
                0
              ],
              "max_abs_delta": 0.06168219819664955,
              "p99_abs_delta": 0.0003950074315071106,
              "residual_rms": 0.0001926285759140388
            }
          ]
        },
        {
          "product": "field-MFS-model-pb.fits.fz",
          "kind": "image",
          "hdu_index": 1,
          "hdu_name": "COMPRESSED_IMAGE",
          "shape": [
            1,
            1,
            2400,
            2400
          ],
          "reference_count": 5760000,
          "reference_mean": 5.671883480712306e-06,
          "reference_std": 0.0038031024251028024,
          "reference_rms": 0.0038031066545765844,
          "reference_min": -0.22202131152153015,
          "reference_max": 2.834251880645752,
          "current_count": 5760000,
          "current_mean": 5.129429852185672e-06,
          "current_std": 0.003790804264531334,
          "current_rms": 0.0037908077349081684,
          "current_min": -0.22202354669570923,
          "current_max": 3.081184148788452,
          "residual_count": 5760000,
          "residual_mean": -5.42453628526634e-07,
          "residual_std": 0.004621291939420675,
          "residual_rms": 0.004621291971257653,
          "residual_min": -0.44093525409698486,
          "residual_max": 0.4340052306652069,
          "reference_mad_std": 0.0,
          "residual_mad_std": 0.0,
          "max_abs_delta": 0.44093525409698486,
          "max_relative_delta": 10601.691376439563,
          "p50_abs_delta": 0.0,
          "p95_abs_delta": 0.0,
          "p99_abs_delta": 0.0,
          "p999_abs_delta": 0.05341396100656427,
          "residual_rms_over_reference_rms": 1.2151360429759392,
          "residual_rms_over_reference_mad_std": null,
          "planes": [
            {
              "plane": 0,
              "leading_index": [
                0,
                0
              ],
              "max_abs_delta": 0.44093525409698486,
              "p99_abs_delta": 0.0,
              "residual_rms": 0.004621291971257653
            }
          ]
        },
        {
          "product": "field-MFS-residual.fits.fz",
          "kind": "image",
          "hdu_index": 1,
          "hdu_name": "COMPRESSED_IMAGE",
          "shape": [
            1,
            1,
            2400,
            2400
          ],
          "reference_count": 5760000,
          "reference_mean": -0.0002231709465173556,
          "reference_std": 0.046052699182433265,
          "reference_rms": 0.04605323992141121,
          "reference_min": -0.22454825043678284,
          "reference_max": 0.22133062779903412,
          "current_count": 5760000,
          "current_mean": -0.00022313612851202215,
          "current_std": 0.0460530147281577,
          "current_rms": 0.04605355529471914,
          "current_min": -0.22453345358371735,
          "current_max": 0.22132427990436554,
          "residual_count": 5760000,
          "residual_mean": 3.481800533320275e-08,
          "residual_std": 0.00019388540977764086,
          "residual_rms": 0.00019388541290395515,
          "residual_min": -0.05330580659210682,
          "residual_max": 0.061682650935836136,
          "reference_mad_std": 0.04521870698896818,
          "residual_mad_std": 0.00014426377415657042,
          "max_abs_delta": 0.061682650935836136,
          "max_relative_delta": 398.30179036925983,
          "p50_abs_delta": 9.73045825958252e-05,
          "p95_abs_delta": 0.0002921745181083679,
          "p99_abs_delta": 0.000396579043008387,
          "p999_abs_delta": 0.000646814741194289,
          "residual_rms_over_reference_rms": 0.0042100276383337226,
          "residual_rms_over_reference_mad_std": 0.00428772571827975,
          "planes": [
            {
              "plane": 0,
              "leading_index": [
                0,
                0
              ],
              "max_abs_delta": 0.061682650935836136,
              "p99_abs_delta": 0.000396579043008387,
              "residual_rms": 0.00019388541290395515
            }
          ]
        },
        {
          "product": "field-MFS-dirty.fits",
          "kind": "image",
          "hdu_index": 0,
          "hdu_name": "PRIMARY",
          "shape": [
            1,
            1,
            2400,
            2400
          ],
          "reference_count": 5760000,
          "reference_mean": -0.0003435230627830375,
          "reference_std": 0.17167440930975023,
          "reference_rms": 0.17167475300680152,
          "reference_min": -0.7124975919723511,
          "reference_max": 4.510988235473633,
          "current_count": 5760000,
          "current_mean": -0.00034176285842805397,
          "current_std": 0.1716702158517139,
          "current_rms": 0.17167055604391054,
          "current_min": -0.7126498818397522,
          "current_max": 4.511445999145508,
          "residual_count": 5760000,
          "residual_mean": 1.7602043549833888e-06,
          "residual_std": 0.002036612550949114,
          "residual_rms": 0.0020366133116040534,
          "residual_min": -0.01647539623081684,
          "residual_max": 0.018678363412618637,
          "reference_mad_std": 0.15400923084332607,
          "residual_mad_std": 0.0005147322624921799,
          "max_abs_delta": 0.018678363412618637,
          "max_relative_delta": 7667.75591290525,
          "p50_abs_delta": 0.00034718215465545654,
          "p95_abs_delta": 0.004815094545483588,
          "p99_abs_delta": 0.007895916812121866,
          "p999_abs_delta": 0.011804465355584819,
          "residual_rms_over_reference_rms": 0.01186320804855543,
          "residual_rms_over_reference_mad_std": 0.01322396911179892,
          "planes": [
            {
              "plane": 0,
              "leading_index": [
                0,
                0
              ],
              "max_abs_delta": 0.018678363412618637,
              "p99_abs_delta": 0.007895916812121866,
              "residual_rms": 0.0020366133116040534
            }
          ]
        },
        {
          "product": "field-MFS-image-pb-ast.fits",
          "kind": "image",
          "hdu_index": 0,
          "hdu_name": "PRIMARY",
          "shape": [
            1,
            1,
            2400,
            2400
          ],
          "reference_count": 5760000,
          "reference_mean": 0.002759588787475192,
          "reference_std": 0.07884962207058553,
          "reference_rms": 0.07889789750652505,
          "reference_min": -0.13746264576911926,
          "reference_max": 4.7501702308654785,
          "current_count": 5760000,
          "current_mean": 0.0027592382603840136,
          "current_std": 0.07884992435271228,
          "current_rms": 0.07889818734423512,
          "current_min": -0.1372925043106079,
          "current_max": 4.750296115875244,
          "residual_count": 5760000,
          "residual_mean": -3.50527091177042e-07,
          "residual_std": 0.00046382384963986506,
          "residual_rms": 0.00046382398209233,
          "residual_min": -0.004474155604839325,
          "residual_max": 0.003575297072529793,
          "reference_mad_std": 0.02822181874511589,
          "residual_mad_std": 0.0003518693972378969,
          "max_abs_delta": 0.004474155604839325,
          "max_relative_delta": 1506.6506906644295,
          "p50_abs_delta": 0.000237341970205307,
          "p95_abs_delta": 0.0009599998826161026,
          "p99_abs_delta": 0.0015816949307918549,
          "p999_abs_delta": 0.002592483546584857,
          "residual_rms_over_reference_rms": 0.005878787607159882,
          "residual_rms_over_reference_mad_std": 0.01643494298795325,
          "planes": [
            {
              "plane": 0,
              "leading_index": [
                0,
                0
              ],
              "max_abs_delta": 0.004474155604839325,
              "p99_abs_delta": 0.0015816949307918549,
              "residual_rms": 0.00046382398209233
            }
          ]
        },
        {
          "product": "field-MFS-image-pb.fits",
          "kind": "image",
          "hdu_index": 0,
          "hdu_name": "PRIMARY",
          "shape": [
            1,
            1,
            2400,
            2400
          ],
          "reference_count": 5760000,
          "reference_mean": 0.002759588787475192,
          "reference_std": 0.07884962207058553,
          "reference_rms": 0.07889789750652505,
          "reference_min": -0.13746264576911926,
          "reference_max": 4.7501702308654785,
          "current_count": 5760000,
          "current_mean": 0.0027592382603840136,
          "current_std": 0.07884992435271228,
          "current_rms": 0.07889818734423512,
          "current_min": -0.1372925043106079,
          "current_max": 4.750296115875244,
          "residual_count": 5760000,
          "residual_mean": -3.50527091177042e-07,
          "residual_std": 0.00046382384963986506,
          "residual_rms": 0.00046382398209233,
          "residual_min": -0.004474155604839325,
          "residual_max": 0.003575297072529793,
          "reference_mad_std": 0.02822181874511589,
          "residual_mad_std": 0.0003518693972378969,
          "max_abs_delta": 0.004474155604839325,
          "max_relative_delta": 1506.6506906644295,
          "p50_abs_delta": 0.000237341970205307,
          "p95_abs_delta": 0.0009599998826161026,
          "p99_abs_delta": 0.0015816949307918549,
          "p999_abs_delta": 0.002592483546584857,
          "residual_rms_over_reference_rms": 0.005878787607159882,
          "residual_rms_over_reference_mad_std": 0.01643494298795325,
          "planes": [
            {
              "plane": 0,
              "leading_index": [
                0,
                0
              ],
              "max_abs_delta": 0.004474155604839325,
              "p99_abs_delta": 0.0015816949307918549,
              "residual_rms": 0.00046382398209233
            }
          ]
        },
        {
          "product": "field-MFS-image.fits",
          "kind": "image",
          "hdu_index": 0,
          "hdu_name": "PRIMARY",
          "shape": [
            1,
            1,
            2400,
            2400
          ],
          "reference_count": 5760000,
          "reference_mean": 0.002720914158630209,
          "reference_std": 0.07778144906170696,
          "reference_rms": 0.0778290253825496,
          "reference_min": -0.13742835819721222,
          "reference_max": 4.750150680541992,
          "current_count": 5760000,
          "current_mean": 0.0027205644654002157,
          "current_std": 0.0777817655740111,
          "current_rms": 0.07782932947688048,
          "current_min": -0.13725827634334564,
          "current_max": 4.750277519226074,
          "residual_count": 5760000,
          "residual_mean": -3.4969322999646106e-07,
          "residual_std": 0.00045157876931408645,
          "residual_rms": 0.0004515789047116572,
          "residual_min": -0.004321582615375519,
          "residual_max": 0.0034651323221623898,
          "reference_mad_std": 0.027650135115534064,
          "residual_mad_std": 0.00034520023539662357,
          "max_abs_delta": 0.004321582615375519,
          "max_relative_delta": 1516.3366159532652,
          "p50_abs_delta": 0.00023283809423446655,
          "p95_abs_delta": 0.000934400552068837,
          "p99_abs_delta": 0.0015304760634899106,
          "p999_abs_delta": 0.0024999157264829416,
          "residual_rms_over_reference_rms": 0.005802191438117479,
          "residual_rms_over_reference_mad_std": 0.016331887812655085,
          "planes": [
            {
              "plane": 0,
              "leading_index": [
                0,
                0
              ],
              "max_abs_delta": 0.004321582615375519,
              "p99_abs_delta": 0.0015304760634899106,
              "residual_rms": 0.0004515789047116572
            }
          ]
        },
        {
          "product": "field-MFS-model-pb.fits",
          "kind": "image",
          "hdu_index": 0,
          "hdu_name": "PRIMARY",
          "shape": [
            1,
            1,
            2400,
            2400
          ],
          "reference_count": 5760000,
          "reference_mean": 2.893908618393147e-06,
          "reference_std": 0.001971754245206158,
          "reference_rms": 0.0019717563688740965,
          "reference_min": 0.0,
          "reference_max": 2.8066883087158203,
          "current_count": 5760000,
          "current_mean": 2.893892338680517e-06,
          "current_std": 0.0019696440778046616,
          "current_rms": 0.001969646203723844,
          "current_min": 0.0,
          "current_max": 2.7986338138580322,
          "residual_count": 5760000,
          "residual_mean": -1.6279712629814943e-11,
          "residual_std": 4.8941675473283696e-05,
          "residual_rms": 4.894167547328689e-05,
          "residual_min": -0.07455606386065483,
          "residual_max": 0.06024436093866825,
          "reference_mad_std": 0.0,
          "residual_mad_std": 0.0,
          "max_abs_delta": 0.07455606386065483,
          "max_relative_delta": 24061.553180217743,
          "p50_abs_delta": 0.0,
          "p95_abs_delta": 0.0,
          "p99_abs_delta": 0.0,
          "p999_abs_delta": 0.0,
          "residual_rms_over_reference_rms": 0.024821360410380387,
          "residual_rms_over_reference_mad_std": null,
          "planes": [
            {
              "plane": 0,
              "leading_index": [
                0,
                0
              ],
              "max_abs_delta": 0.07455606386065483,
              "p99_abs_delta": 0.0,
              "residual_rms": 4.894167547328689e-05
            }
          ]
        },
        {
          "product": "field-MFS-residual.fits",
          "kind": "image",
          "hdu_index": 0,
          "hdu_name": "PRIMARY",
          "shape": [
            1,
            1,
            2400,
            2400
          ],
          "reference_count": 5760000,
          "reference_mean": -3.682864820725986e-05,
          "reference_std": 0.02901050530105403,
          "reference_rms": 0.029010528677909594,
          "reference_min": -0.1397465467453003,
          "reference_max": 0.3134484887123108,
          "current_count": 5760000,
          "current_mean": -3.716343633993026e-05,
          "current_std": 0.029013208868711813,
          "current_rms": 0.029013232670291975,
          "current_min": -0.13956958055496216,
          "current_max": 0.31340330839157104,
          "residual_count": 5760000,
          "residual_mean": -3.347881326704352e-07,
          "residual_std": 0.0004498733579346937,
          "residual_rms": 0.0004498734825065053,
          "residual_min": -0.004321552813053131,
          "residual_max": 0.00346513744443655,
          "reference_mad_std": 0.027609810289082815,
          "residual_mad_std": 0.0003451836660504341,
          "max_abs_delta": 0.004321552813053131,
          "max_relative_delta": 1510.431540718223,
          "p50_abs_delta": 0.0002328231930732727,
          "p95_abs_delta": 0.0009306250605732201,
          "p99_abs_delta": 0.0015194770134985443,
          "p999_abs_delta": 0.0024748966284096445,
          "residual_rms_over_reference_rms": 0.015507248678617384,
          "residual_rms_over_reference_mad_std": 0.01629397224378574,
          "planes": [
            {
              "plane": 0,
              "leading_index": [
                0,
                0
              ],
              "max_abs_delta": 0.004321552813053131,
              "p99_abs_delta": 0.0015194770134985443,
              "residual_rms": 0.0004498734825065053
            }
          ]
        },
        {
          "product": "sector_1.source_catalog.fits",
          "kind": "table",
          "hdu_index": 1,
          "hdu_name": "",
          "rows": 10,
          "columns": [
            "Source_id",
            "Isl_id",
            "RA",
            "E_RA",
            "DEC",
            "E_DEC",
            "Total_flux",
            "E_Total_flux",
            "Peak_flux",
            "E_Peak_flux",
            "RA_max",
            "E_RA_max",
            "DEC_max",
            "E_DEC_max",
            "Maj",
            "E_Maj",
            "Min",
            "E_Min",
            "PA",
            "E_PA",
            "Maj_img_plane",
            "E_Maj_img_plane",
            "Min_img_plane",
            "E_Min_img_plane",
            "PA_img_plane",
            "E_PA_img_plane",
            "DC_Maj",
            "E_DC_Maj",
            "DC_Min",
            "E_DC_Min",
            "DC_PA",
            "E_DC_PA",
            "DC_Maj_img_plane",
            "E_DC_Maj_img_plane",
            "DC_Min_img_plane",
            "E_DC_Min_img_plane",
            "DC_PA_img_plane",
            "E_DC_PA_img_plane",
            "Isl_Total_flux",
            "E_Isl_Total_flux",
            "Isl_rms",
            "Isl_mean",
            "Resid_Isl_rms",
            "Resid_Isl_mean",
            "S_Code"
          ]
        },
        {
          "product": "sector_1.source_catalog.fits",
          "kind": "table",
          "hdu_index": 1,
          "hdu_name": "",
          "rows": 11,
          "columns": [
            "Source_id",
            "Isl_id",
            "RA",
            "E_RA",
            "DEC",
            "E_DEC",
            "Total_flux",
            "E_Total_flux",
            "Peak_flux",
            "E_Peak_flux",
            "RA_max",
            "E_RA_max",
            "DEC_max",
            "E_DEC_max",
            "Maj",
            "E_Maj",
            "Min",
            "E_Min",
            "PA",
            "E_PA",
            "Maj_img_plane",
            "E_Maj_img_plane",
            "Min_img_plane",
            "E_Min_img_plane",
            "PA_img_plane",
            "E_PA_img_plane",
            "DC_Maj",
            "E_DC_Maj",
            "DC_Min",
            "E_DC_Min",
            "DC_PA",
            "E_DC_PA",
            "DC_Maj_img_plane",
            "E_DC_Maj_img_plane",
            "DC_Min_img_plane",
            "E_DC_Min_img_plane",
            "DC_PA_img_plane",
            "E_DC_PA_img_plane",
            "Isl_Total_flux",
            "E_Isl_Total_flux",
            "Isl_rms",
            "Isl_mean",
            "Resid_Isl_rms",
            "Resid_Isl_mean",
            "S_Code"
          ]
        },
        {
          "product": "sector_1.source_catalog.fits",
          "kind": "table",
          "hdu_index": 1,
          "hdu_name": "",
          "rows": 11,
          "columns": [
            "Source_id",
            "Isl_id",
            "RA",
            "E_RA",
            "DEC",
            "E_DEC",
            "Total_flux",
            "E_Total_flux",
            "Peak_flux",
            "E_Peak_flux",
            "RA_max",
            "E_RA_max",
            "DEC_max",
            "E_DEC_max",
            "Maj",
            "E_Maj",
            "Min",
            "E_Min",
            "PA",
            "E_PA",
            "Maj_img_plane",
            "E_Maj_img_plane",
            "Min_img_plane",
            "E_Min_img_plane",
            "PA_img_plane",
            "E_PA_img_plane",
            "DC_Maj",
            "E_DC_Maj",
            "DC_Min",
            "E_DC_Min",
            "DC_PA",
            "E_DC_PA",
            "DC_Maj_img_plane",
            "E_DC_Maj_img_plane",
            "DC_Min_img_plane",
            "E_DC_Min_img_plane",
            "DC_PA_img_plane",
            "E_DC_PA_img_plane",
            "Isl_Total_flux",
            "E_Isl_Total_flux",
            "Isl_rms",
            "Isl_mean",
            "Resid_Isl_rms",
            "Resid_Isl_mean",
            "S_Code"
          ]
        },
        {
          "product": "sector_1.source_catalog.fits",
          "kind": "table",
          "hdu_index": 1,
          "hdu_name": "",
          "rows": 11,
          "columns": [
            "Source_id",
            "Isl_id",
            "RA",
            "E_RA",
            "DEC",
            "E_DEC",
            "Total_flux",
            "E_Total_flux",
            "Peak_flux",
            "E_Peak_flux",
            "RA_max",
            "E_RA_max",
            "DEC_max",
            "E_DEC_max",
            "Maj",
            "E_Maj",
            "Min",
            "E_Min",
            "PA",
            "E_PA",
            "Maj_img_plane",
            "E_Maj_img_plane",
            "Min_img_plane",
            "E_Min_img_plane",
            "PA_img_plane",
            "E_PA_img_plane",
            "DC_Maj",
            "E_DC_Maj",
            "DC_Min",
            "E_DC_Min",
            "DC_PA",
            "E_DC_PA",
            "DC_Maj_img_plane",
            "E_DC_Maj_img_plane",
            "DC_Min_img_plane",
            "E_DC_Min_img_plane",
            "DC_PA_img_plane",
            "E_DC_PA_img_plane",
            "Isl_Total_flux",
            "E_Isl_Total_flux",
            "Isl_rms",
            "Isl_mean",
            "Resid_Isl_rms",
            "Resid_Isl_mean",
            "S_Code"
          ]
        }
      ],
      "diagnostics": [
        {
          "operation": "image_1",
          "sector": "sector_1",
          "field": "nsources",
          "reference": 10.0,
          "current": 10.0,
          "delta": 0.0,
          "relative_delta": 0.0
        },
        {
          "operation": "image_1",
          "sector": "sector_1",
          "field": "theoretical_rms",
          "reference": 0.009006402987775022,
          "current": 0.009006402987775022,
          "delta": 0.0,
          "relative_delta": 0.0
        },
        {
          "operation": "image_1",
          "sector": "sector_1",
          "field": "min_rms_flat_noise",
          "reference": 0.019869254902005196,
          "current": 0.01986919716000557,
          "delta": -5.774199962615967e-08,
          "relative_delta": -2.9060978839388874e-06
        },
        {
          "operation": "image_1",
          "sector": "sector_1",
          "field": "median_rms_flat_noise",
          "reference": 0.03982412815093994,
          "current": 0.03982412442564964,
          "delta": -3.725290298461914e-09,
          "relative_delta": -9.354354938650399e-08
        },
        {
          "operation": "image_1",
          "sector": "sector_1",
          "field": "dynamic_range_global_flat_noise",
          "reference": 229.59130233026866,
          "current": 229.59199354581907,
          "delta": 0.0006912155504039674,
          "relative_delta": 3.0106347382865975e-06
        },
        {
          "operation": "image_1",
          "sector": "sector_1",
          "field": "min_rms_true_sky",
          "reference": 0.020377833396196365,
          "current": 0.020377829670906067,
          "delta": -3.725290298461914e-09,
          "relative_delta": -1.8281091154456392e-07
        },
        {
          "operation": "image_1",
          "sector": "sector_1",
          "field": "median_rms_true_sky",
          "reference": 0.04061480239033699,
          "current": 0.04061480239033699,
          "delta": 0.0,
          "relative_delta": 0.0
        },
        {
          "operation": "image_1",
          "sector": "sector_1",
          "field": "dynamic_range_global_true_sky",
          "reference": 223.86166625199058,
          "current": 223.86170717635332,
          "delta": 4.0924362735950126e-05,
          "relative_delta": 1.8281094490685819e-07
        },
        {
          "operation": "image_2",
          "sector": "sector_1",
          "field": "nsources",
          "reference": 11.0,
          "current": 11.0,
          "delta": 0.0,
          "relative_delta": 0.0
        },
        {
          "operation": "image_2",
          "sector": "sector_1",
          "field": "theoretical_rms",
          "reference": 0.009006402987775022,
          "current": 0.009006402987775022,
          "delta": 0.0,
          "relative_delta": 0.0
        },
        {
          "operation": "image_2",
          "sector": "sector_1",
          "field": "min_rms_flat_noise",
          "reference": 0.030124466866254807,
          "current": 0.030141068622469902,
          "delta": 1.660175621509552e-05,
          "relative_delta": 0.0005511053951196287
        },
        {
          "operation": "image_2",
          "sector": "sector_1",
          "field": "median_rms_flat_noise",
          "reference": 0.043648697435855865,
          "current": 0.04364601522684097,
          "delta": -2.682209014892578e-06,
          "relative_delta": -6.144992113073317e-05
        },
        {
          "operation": "image_2",
          "sector": "sector_1",
          "field": "dynamic_range_global_flat_noise",
          "reference": 154.29884591246494,
          "current": 154.21487031499402,
          "delta": -0.08397559747092487,
          "relative_delta": -0.000544239958337504
        },
        {
          "operation": "image_2",
          "sector": "sector_1",
          "field": "min_rms_true_sky",
          "reference": 0.030120721086859703,
          "current": 0.03013787791132927,
          "delta": 1.7156824469566345e-05,
          "relative_delta": 0.0005696020497016283
        },
        {
          "operation": "image_2",
          "sector": "sector_1",
          "field": "median_rms_true_sky",
          "reference": 0.04452504217624664,
          "current": 0.044521868228912354,
          "delta": -3.1739473342895508e-06,
          "relative_delta": -7.128454413868693e-05
        },
        {
          "operation": "image_2",
          "sector": "sector_1",
          "field": "dynamic_range_global_true_sky",
          "reference": 154.318398455402,
          "current": 154.23154519581092,
          "delta": -0.08685325959106649,
          "relative_delta": -0.0005628185651250591
        },
        {
          "operation": "image_3",
          "sector": "sector_1",
          "field": "nsources",
          "reference": 11.0,
          "current": 11.0,
          "delta": 0.0,
          "relative_delta": 0.0
        },
        {
          "operation": "image_3",
          "sector": "sector_1",
          "field": "theoretical_rms",
          "reference": 0.009006402987775022,
          "current": 0.009006402987775022,
          "delta": 0.0,
          "relative_delta": 0.0
        },
        {
          "operation": "image_3",
          "sector": "sector_1",
          "field": "min_rms_flat_noise",
          "reference": 0.030658666044473648,
          "current": 0.030657682567834854,
          "delta": -9.834766387939453e-07,
          "relative_delta": -3.207825928784077e-05
        },
        {
          "operation": "image_3",
          "sector": "sector_1",
          "field": "median_rms_flat_noise",
          "reference": 0.044137872755527496,
          "current": 0.044135138392448425,
          "delta": -2.734363079071045e-06,
          "relative_delta": -6.19504953085582e-05
        },
        {
          "operation": "image_3",
          "sector": "sector_1",
          "field": "dynamic_range_global_flat_noise",
          "reference": 152.27195851017385,
          "current": 152.28443344027644,
          "delta": 0.012474930102598591,
          "relative_delta": 8.192532771399992e-05
        },
        {
          "operation": "image_3",
          "sector": "sector_1",
          "field": "min_rms_true_sky",
          "reference": 0.030654260888695717,
          "current": 0.030653543770313263,
          "delta": -7.171183824539185e-07,
          "relative_delta": -2.339375870316182e-05
        },
        {
          "operation": "image_3",
          "sector": "sector_1",
          "field": "median_rms_true_sky",
          "reference": 0.045030780136585236,
          "current": 0.045029520988464355,
          "delta": -1.259148120880127e-06,
          "relative_delta": -2.796194329880447e-05
        },
        {
          "operation": "image_3",
          "sector": "sector_1",
          "field": "dynamic_range_global_true_sky",
          "reference": 152.29430733845197,
          "current": 152.30547689262366,
          "delta": 0.011169554171686968,
          "relative_delta": 7.334190205064105e-05
        },
        {
          "operation": "image_4",
          "sector": "sector_1",
          "field": "nsources",
          "reference": 11.0,
          "current": 11.0,
          "delta": 0.0,
          "relative_delta": 0.0
        },
        {
          "operation": "image_4",
          "sector": "sector_1",
          "field": "theoretical_rms",
          "reference": 0.009006402987775022,
          "current": 0.009006402987775022,
          "delta": 0.0,
          "relative_delta": 0.0
        },
        {
          "operation": "image_4",
          "sector": "sector_1",
          "field": "min_rms_flat_noise",
          "reference": 0.016093745827674866,
          "current": 0.016059719026088715,
          "delta": -3.402680158615112e-05,
          "relative_delta": -0.0021142872486303657
        },
        {
          "operation": "image_4",
          "sector": "sector_1",
          "field": "median_rms_flat_noise",
          "reference": 0.02723381295800209,
          "current": 0.027238521724939346,
          "delta": 4.708766937255859e-06,
          "relative_delta": 0.000172901493614477
        },
        {
          "operation": "image_4",
          "sector": "sector_1",
          "field": "dynamic_range_global_flat_noise",
          "reference": 295.155070261742,
          "current": 295.78833300317,
          "delta": 0.6332627414279841,
          "relative_delta": 0.0021455255397320803
        },
        {
          "operation": "image_4",
          "sector": "sector_1",
          "field": "min_rms_true_sky",
          "reference": 0.016097914427518845,
          "current": 0.016061676666140556,
          "delta": -3.623776137828827e-05,
          "relative_delta": -0.0022510842346348315
        },
        {
          "operation": "image_4",
          "sector": "sector_1",
          "field": "median_rms_true_sky",
          "reference": 0.02780814841389656,
          "current": 0.02781350165605545,
          "delta": 5.3532421588897705e-06,
          "relative_delta": 0.00019250624238665944
        },
        {
          "operation": "image_4",
          "sector": "sector_1",
          "field": "dynamic_range_global_true_sky",
          "reference": 295.0798534961288,
          "current": 295.75343935850054,
          "delta": 0.6735858623717377,
          "relative_delta": 0.002282723996203199
        }
      ],
      "visual_comparisons": [
        {
          "kind": "image",
          "label": "image_1/field-MFS-image-pb-ast.fits.fz",
          "path": "visual-comparisons/images/image_1-field-mfs-image-pb-ast.fits.fz.png"
        },
        {
          "kind": "image",
          "label": "image_1/field-MFS-image-pb.fits.fz",
          "path": "visual-comparisons/images/image_1-field-mfs-image-pb.fits.fz.png"
        },
        {
          "kind": "image",
          "label": "image_1/field-MFS-residual.fits.fz",
          "path": "visual-comparisons/images/image_1-field-mfs-residual.fits.fz.png"
        },
        {
          "kind": "image",
          "label": "image_2/field-MFS-image-pb-ast.fits.fz",
          "path": "visual-comparisons/images/image_2-field-mfs-image-pb-ast.fits.fz.png"
        },
        {
          "kind": "image",
          "label": "image_2/field-MFS-image-pb.fits.fz",
          "path": "visual-comparisons/images/image_2-field-mfs-image-pb.fits.fz.png"
        },
        {
          "kind": "image",
          "label": "image_2/field-MFS-residual.fits.fz",
          "path": "visual-comparisons/images/image_2-field-mfs-residual.fits.fz.png"
        },
        {
          "kind": "image",
          "label": "image_3/field-MFS-image-pb-ast.fits.fz",
          "path": "visual-comparisons/images/image_3-field-mfs-image-pb-ast.fits.fz.png"
        },
        {
          "kind": "image",
          "label": "image_3/field-MFS-image-pb.fits.fz",
          "path": "visual-comparisons/images/image_3-field-mfs-image-pb.fits.fz.png"
        },
        {
          "kind": "image",
          "label": "image_3/field-MFS-residual.fits.fz",
          "path": "visual-comparisons/images/image_3-field-mfs-residual.fits.fz.png"
        },
        {
          "kind": "image",
          "label": "image_4/field-MFS-image-pb-ast.fits",
          "path": "visual-comparisons/images/image_4-field-mfs-image-pb-ast.fits.png"
        },
        {
          "kind": "image",
          "label": "image_4/field-MFS-image-pb.fits",
          "path": "visual-comparisons/images/image_4-field-mfs-image-pb.fits.png"
        },
        {
          "kind": "image",
          "label": "image_4/field-MFS-residual.fits",
          "path": "visual-comparisons/images/image_4-field-mfs-residual.fits.png"
        },
        {
          "kind": "solution",
          "label": "calibrate_1/fast_phase_dir[Patch_rich_centre].png",
          "path": "visual-comparisons/solutions/calibrate_1-fast_phase_dir-patch_rich_centre-.png.png"
        },
        {
          "kind": "solution",
          "label": "calibrate_1/medium1_phase_dir[Patch_rich_centre].png",
          "path": "visual-comparisons/solutions/calibrate_1-medium1_phase_dir-patch_rich_centre-.png.png"
        },
        {
          "kind": "solution",
          "label": "calibrate_2/fast_phase_dir[Patch_0].png",
          "path": "visual-comparisons/solutions/calibrate_2-fast_phase_dir-patch_0-.png.png"
        },
        {
          "kind": "solution",
          "label": "calibrate_2/medium1_phase_dir[Patch_0].png",
          "path": "visual-comparisons/solutions/calibrate_2-medium1_phase_dir-patch_0-.png.png"
        },
        {
          "kind": "solution",
          "label": "calibrate_3/fast_phase_dir[Patch_0].png",
          "path": "visual-comparisons/solutions/calibrate_3-fast_phase_dir-patch_0-.png.png"
        },
        {
          "kind": "solution",
          "label": "calibrate_3/medium1_phase_dir[Patch_0].png",
          "path": "visual-comparisons/solutions/calibrate_3-medium1_phase_dir-patch_0-.png.png"
        },
        {
          "kind": "solution",
          "label": "calibrate_4/fast_phase_dir[Patch_patch_10_sector_1].png",
          "path": "visual-comparisons/solutions/calibrate_4-fast_phase_dir-patch_patch_10_sector_1-.png.png"
        },
        {
          "kind": "solution",
          "label": "calibrate_4/medium1_phase_dir[Patch_patch_10_sector_1].png",
          "path": "visual-comparisons/solutions/calibrate_4-medium1_phase_dir-patch_patch_10_sector_1-.png.png"
        }
      ]
    },
    "failures": [
      "FITS image pixels differ for field-MFS-dirty.fits.fz: max_abs_delta=1.4659017324447632e-05, p99_abs_delta=9.939074516296387e-06, residual_rms=4.1553033187139075e-06",
      "FITS image pixels differ for field-MFS-image-pb-ast.fits.fz: max_abs_delta=0.018093821592628956, p99_abs_delta=2.8472859412431717e-06, residual_rms=7.632951753680657e-06",
      "FITS image pixels differ for field-MFS-image-pb.fits.fz: max_abs_delta=0.01809362042695284, p99_abs_delta=2.8461217880249023e-06, residual_rms=7.632750976209149e-06",
      "FITS image pixels differ for field-MFS-image.fits.fz: max_abs_delta=0.01772800786420703, p99_abs_delta=2.7939677238464355e-06, residual_rms=7.478624511124676e-06",
      "FITS std differs for field-MFS-model-pb.fits.fz: 0.0030398209669020232 != 0.0030222728774504212",
      "FITS rms differs for field-MFS-model-pb.fits.fz: 0.0030398246163428604 != 0.0030222771821346037",
      "FITS max differs for field-MFS-model-pb.fits.fz: 1.6757864952087402 != 1.6649447679519653",
      "FITS image pixels differ for field-MFS-model-pb.fits.fz: max_abs_delta=0.23139111697673798, p99_abs_delta=0.0, residual_rms=0.003443491680569351",
      "FITS image pixels differ for field-MFS-residual.fits.fz: max_abs_delta=0.017727395053952932, p99_abs_delta=2.773478627204895e-06, residual_rms=7.477155436964352e-06",
      "FITS image pixels differ for field-MFS-dirty.fits.fz: max_abs_delta=1.4096498489379883e-05, p99_abs_delta=9.901821613311768e-06, residual_rms=4.157352385970752e-06",
      "FITS image pixels differ for field-MFS-image-pb-ast.fits.fz: max_abs_delta=0.052141185849905014, p99_abs_delta=0.0001289844512939453, residual_rms=8.313823482811896e-05",
      "FITS image pixels differ for field-MFS-image-pb.fits.fz: max_abs_delta=0.05214239377528429, p99_abs_delta=0.00012901145964860916, residual_rms=8.313734194560421e-05",
      "FITS image pixels differ for field-MFS-image.fits.fz: max_abs_delta=0.05199414771050215, p99_abs_delta=0.0001267567276954651, residual_rms=8.230196253269788e-05",
      "FITS image pixels differ for field-MFS-model-pb.fits.fz: max_abs_delta=0.16418200731277466, p99_abs_delta=0.0, residual_rms=0.0027073598071415557",
      "FITS image pixels differ for field-MFS-residual.fits.fz: max_abs_delta=0.05199167225509882, p99_abs_delta=0.0001301020383834839, residual_rms=8.69619171110662e-05",
      "FITS image pixels differ for field-MFS-dirty.fits.fz: max_abs_delta=0.0016504526138305664, p99_abs_delta=0.00027060514781623943, residual_rms=8.17961024809948e-05",
      "FITS image pixels differ for field-MFS-image-pb-ast.fits.fz: max_abs_delta=0.06172359955962747, p99_abs_delta=0.0004034182149916885, residual_rms=0.00019586462348565944",
      "FITS image pixels differ for field-MFS-image-pb.fits.fz: max_abs_delta=0.061724577797576785, p99_abs_delta=0.0004034265875816345, residual_rms=0.00019586365755285446",
      "FITS image pixels differ for field-MFS-image.fits.fz: max_abs_delta=0.06168219819664955, p99_abs_delta=0.0003950074315071106, residual_rms=0.0001926285759140388",
      "FITS std differs for field-MFS-model-pb.fits.fz: 0.0038031024251028024 != 0.003790804264531334",
      "FITS rms differs for field-MFS-model-pb.fits.fz: 0.0038031066545765844 != 0.0037908077349081684",
      "FITS max differs for field-MFS-model-pb.fits.fz: 2.834251880645752 != 3.081184148788452",
      "FITS image pixels differ for field-MFS-model-pb.fits.fz: max_abs_delta=0.44093525409698486, p99_abs_delta=0.0, residual_rms=0.004621291971257653",
      "FITS image pixels differ for field-MFS-residual.fits.fz: max_abs_delta=0.061682650935836136, p99_abs_delta=0.000396579043008387, residual_rms=0.00019388541290395515",
      "FITS mean differs for field-MFS-dirty.fits: -0.0003435230627830375 != -0.00034176285842805397",
      "FITS image pixels differ for field-MFS-dirty.fits: max_abs_delta=0.018678363412618637, p99_abs_delta=0.007895916812121866, residual_rms=0.0020366133116040534",
      "FITS min differs for field-MFS-image-pb-ast.fits: -0.13746264576911926 != -0.1372925043106079",
      "FITS image pixels differ for field-MFS-image-pb-ast.fits: max_abs_delta=0.004474155604839325, p99_abs_delta=0.0015816949307918549, residual_rms=0.00046382398209233",
      "FITS min differs for field-MFS-image-pb.fits: -0.13746264576911926 != -0.1372925043106079",
      "FITS image pixels differ for field-MFS-image-pb.fits: max_abs_delta=0.004474155604839325, p99_abs_delta=0.0015816949307918549, residual_rms=0.00046382398209233",
      "FITS min differs for field-MFS-image.fits: -0.13742835819721222 != -0.13725827634334564",
      "FITS image pixels differ for field-MFS-image.fits: max_abs_delta=0.004321582615375519, p99_abs_delta=0.0015304760634899106, residual_rms=0.0004515789047116572",
      "FITS max differs for field-MFS-model-pb.fits: 2.8066883087158203 != 2.7986338138580322",
      "FITS image pixels differ for field-MFS-model-pb.fits: max_abs_delta=0.07455606386065483, p99_abs_delta=0.0, residual_rms=4.894167547328689e-05",
      "FITS min differs for field-MFS-residual.fits: -0.1397465467453003 != -0.13956958055496216",
      "FITS image pixels differ for field-MFS-residual.fits: max_abs_delta=0.004321552813053131, p99_abs_delta=0.0015194770134985443, residual_rms=0.0004498734825065053",
      "HDF5 numeric dataset differs for field-solutions-fast-phase.h5:sol000/phase000/val (max_abs=0.00160415)",
      "HDF5 numeric dataset differs for field-solutions.h5:sol000/phase000/val (max_abs=0.00160415)",
      "HDF5 numeric dataset differs for field-solutions-fast-phase.h5:sol000/phase000/val (max_abs=6.11638)",
      "HDF5 dataset differs for field-solutions-fast-phase.h5:sol000/source",
      "HDF5 numeric dataset differs for field-solutions.h5:sol000/phase000/val (max_abs=6.11638)",
      "HDF5 dataset differs for field-solutions.h5:sol000/source",
      "sky-model summary differs for calibration_skymodel.txt",
      "sky-model summary differs for calibrators_only_skymodel.txt",
      "sky-model summary differs for source_skymodel.txt",
      "sky-model summary differs for calibration_skymodel.txt",
      "sky-model summary differs for calibrators_only_skymodel.txt",
      "sky-model summary differs for source_skymodel.txt",
      "sky-model summary differs for sector_1.apparent_sky.txt",
      "FITS table column differs for sector_1.source_catalog.fits:PA",
      "FITS table column differs for sector_1.source_catalog.fits:PA_img_plane",
      "FITS table column differs for sector_1.source_catalog.fits:DC_Min",
      "FITS table column differs for sector_1.source_catalog.fits:DC_PA",
      "FITS table column differs for sector_1.source_catalog.fits:DC_Min_img_plane",
      "FITS table column differs for sector_1.source_catalog.fits:DC_PA_img_plane",
      "FITS table column differs for sector_1.source_catalog.fits:E_Isl_Total_flux",
      "FITS table column differs for sector_1.source_catalog.fits:Resid_Isl_rms",
      "FITS table column differs for sector_1.source_catalog.fits:Resid_Isl_mean",
      "sky-model summary differs for sector_1.true_sky.txt",
      "sky-model summary differs for bright_source_skymodel.txt",
      "sky-model summary differs for sector_1.apparent_sky.txt",
      "FITS table column differs for sector_1.source_catalog.fits:E_DEC",
      "FITS table column differs for sector_1.source_catalog.fits:E_DEC_max",
      "FITS table column differs for sector_1.source_catalog.fits:PA",
      "FITS table column differs for sector_1.source_catalog.fits:E_PA",
      "FITS table column differs for sector_1.source_catalog.fits:PA_img_plane",
      "FITS table column differs for sector_1.source_catalog.fits:E_PA_img_plane",
      "FITS table column differs for sector_1.source_catalog.fits:DC_Maj",
      "FITS table column differs for sector_1.source_catalog.fits:DC_Min",
      "FITS table column differs for sector_1.source_catalog.fits:DC_PA",
      "FITS table column differs for sector_1.source_catalog.fits:E_DC_PA",
      "FITS table column differs for sector_1.source_catalog.fits:DC_Maj_img_plane",
      "FITS table column differs for sector_1.source_catalog.fits:DC_Min_img_plane",
      "FITS table column differs for sector_1.source_catalog.fits:DC_PA_img_plane",
      "FITS table column differs for sector_1.source_catalog.fits:E_DC_PA_img_plane",
      "FITS table column differs for sector_1.source_catalog.fits:Resid_Isl_rms",
      "FITS table column differs for sector_1.source_catalog.fits:Resid_Isl_mean",
      "sky-model summary differs for sector_1.true_sky.txt",
      "sky-model summary differs for bright_source_skymodel.txt",
      "FITS table column differs for sector_1.source_catalog.fits:E_RA",
      "FITS table column differs for sector_1.source_catalog.fits:E_DEC",
      "FITS table column differs for sector_1.source_catalog.fits:Total_flux",
      "FITS table column differs for sector_1.source_catalog.fits:E_Total_flux",
      "FITS table column differs for sector_1.source_catalog.fits:Peak_flux",
      "FITS table column differs for sector_1.source_catalog.fits:E_Peak_flux",
      "FITS table column differs for sector_1.source_catalog.fits:E_RA_max",
      "FITS table column differs for sector_1.source_catalog.fits:E_DEC_max",
      "FITS table column differs for sector_1.source_catalog.fits:Maj",
      "FITS table column differs for sector_1.source_catalog.fits:E_Maj",
      "FITS table column differs for sector_1.source_catalog.fits:Min",
      "FITS table column differs for sector_1.source_catalog.fits:E_Min",
      "FITS table column differs for sector_1.source_catalog.fits:PA",
      "FITS table column differs for sector_1.source_catalog.fits:E_PA",
      "FITS table column differs for sector_1.source_catalog.fits:Maj_img_plane",
      "FITS table column differs for sector_1.source_catalog.fits:E_Maj_img_plane",
      "FITS table column differs for sector_1.source_catalog.fits:Min_img_plane",
      "FITS table column differs for sector_1.source_catalog.fits:E_Min_img_plane",
      "FITS table column differs for sector_1.source_catalog.fits:PA_img_plane",
      "FITS table column differs for sector_1.source_catalog.fits:E_PA_img_plane",
      "FITS table column differs for sector_1.source_catalog.fits:DC_Maj",
      "FITS table column differs for sector_1.source_catalog.fits:E_DC_Maj",
      "FITS table column differs for sector_1.source_catalog.fits:DC_Min",
      "FITS table column differs for sector_1.source_catalog.fits:E_DC_Min",
      "FITS table column differs for sector_1.source_catalog.fits:DC_PA",
      "FITS table column differs for sector_1.source_catalog.fits:E_DC_PA",
      "FITS table column differs for sector_1.source_catalog.fits:DC_Maj_img_plane",
      "FITS table column differs for sector_1.source_catalog.fits:E_DC_Maj_img_plane",
      "FITS table column differs for sector_1.source_catalog.fits:DC_Min_img_plane",
      "FITS table column differs for sector_1.source_catalog.fits:E_DC_Min_img_plane",
      "FITS table column differs for sector_1.source_catalog.fits:DC_PA_img_plane",
      "FITS table column differs for sector_1.source_catalog.fits:E_DC_PA_img_plane",
      "FITS table column differs for sector_1.source_catalog.fits:Isl_Total_flux",
      "FITS table column differs for sector_1.source_catalog.fits:E_Isl_Total_flux",
      "FITS table column differs for sector_1.source_catalog.fits:Isl_rms",
      "FITS table column differs for sector_1.source_catalog.fits:Resid_Isl_rms",
      "FITS table column differs for sector_1.source_catalog.fits:Resid_Isl_mean",
      "sky-model summary differs for predict_1_predict_skymodel.txt",
      "sky-model summary differs for sector_1_predict_skymodel.txt",
      "sky-model summary differs for predict_1_predict_skymodel.txt",
      "sky-model summary differs for sector_1_predict_skymodel.txt",
      "text product differs for sector_1_facets_ds9.reg",
      "text product differs for sector_1_facets_ds9.reg",
      "text product differs for sector_1_facets_ds9.reg",
      "text product differs for sector_1_facets_ds9.reg"
    ],
    "warnings": [
      "output-record summary differs for calibrate_1",
      "output-record summary differs for calibrate_2",
      "output-record summary differs for calibrate_3",
      "output-record summary differs for calibrate_4"
    ]
  }
}
